r321f/__init__.py
r321f/cli/__init__.py
r321f/cli/cr_only.py
r321f/cli/main.py
r321f/cli/tui.py
r321f/cli/tui_main.py
r321f/core/__init__.py
r321f/core/decryptor.py
r321f/core/developer_mode.py
r321f/core/encryption_levels.py
r321f/core/encryptor.py
r321f/core/initializer.py
r321f/core/key_manager.py
r321f/core/stream_crypto.py
r321f/utils/__init__.py
r321f/utils/file_utils.py
r321f/utils/platform_utils.py
r321f-4.0.0.dist-info/licenses/LICENSE
r321f-4.0.0.dist-info/METADATA
r321f-4.0.0.dist-info/WHEEL
r321f-4.0.0.dist-info/entry_points.txt
r321f-4.0.0.dist-info/top_level.txt
r321f-4.0.0.dist-info/RECORD
